olaii_stripe/__init__.py
olaii_stripe/admin.py
olaii_stripe/exceptions.py
olaii_stripe/helpers.py
olaii_stripe/models.py
olaii_stripe/webhook_helpers.py
olaii_stripe/migrations/0001_initial.py
olaii_stripe/migrations/0002_paymentmethod_deleted.py
olaii_stripe/migrations/0003_auto_20191227_1001.py
olaii_stripe/migrations/0004_refund.py
olaii_stripe/migrations/0005_paymentintent_save_payment_method_alter_customer_id_and_more.py
olaii_stripe/migrations/__init__.py
olaii_stripe-0.1.12.dist-info/LICENSE
olaii_stripe-0.1.12.dist-info/METADATA
olaii_stripe-0.1.12.dist-info/WHEEL
olaii_stripe-0.1.12.dist-info/top_level.txt
olaii_stripe-0.1.12.dist-info/RECORD
